{
  "project_info": {
    "project_number": "214890125852",
    "project_id": "agriculture-ai-1856a",
    "storage_bucket": "agriculture-ai-1856a.appspot.com"
  },
  "client": [
    {
      "client_info": {
        "mobilesdk_app_id": "1:214890125852:android:3091fee1fcc2584edf5dd9",
        "android_client_info": {
          "package_name": "com.company.agriculture_Ai"
        }
      },
      "oauth_client": [],
      "api_key": [
        {
          "current_key": "AIzaSyBLj1Wi_y__WbVKtzIZQrtUfWaHxNjxFVw"
        }
      ],
      "services": {
        "appinvite_service": {
          "other_platform_oauth_client": []
        }
      }
    }
  ],
  "configuration_version": "1"
}